oar_cli/__init__.py
oar_cli/db/__init__.py
oar_cli/db/alembic.py
oar_cli/db/operations.py
oar_cli/db/helpers.py
oar_cli/db/commands/__init__.py
oar_cli/db/commands/archive.py
oar_cli/db/commands/migrate.py
oar_cli-0.3.5.dist-info/entry_points.txt
oar_cli-0.3.5.dist-info/metadata.json
oar_cli-0.3.5.dist-info/WHEEL
oar_cli-0.3.5.dist-info/DESCRIPTION.rst
oar_cli-0.3.5.dist-info/top_level.txt
oar_cli-0.3.5.dist-info/RECORD
oar_cli-0.3.5.dist-info/METADATA
