Metadata-Version: 2.0
Name: oar-cli
Version: 0.3.5
Summary: OAR Command line interface.
Home-page: https://github.com/oar-team/python-oar-cli
Author: Salem Harrache
Author-email: salem.harrache@inria.fr
License: GNU GPL
Platform: UNKNOWN
Classifier: Development Status :: 1 - Planning
Classifier: Operating System :: OS Independent
Classifier: Intended Audience :: Developers
Classifier: Programming Language :: Python
Classifier: Programming Language :: Python :: 3
Classifier: License :: OSI Approved :: BSD License
Classifier: License :: OSI Approved :: GNU General Public License (GPL)
Classifier: Topic :: Software Development :: Libraries :: Python Modules
Classifier: Topic :: System :: Clustering
Requires-Dist: oar-lib
Requires-Dist: tabulate
Requires-Dist: click
